mycalc/calculator.py
Sonihi_K-0.2.0.dist-info/METADATA
Sonihi_K-0.2.0.dist-info/WHEEL
Sonihi_K-0.2.0.dist-info/top_level.txt
Sonihi_K-0.2.0.dist-info/RECORD
