Metadata-Version: 2.1
Name: Sonihi-K
Version: 0.2.0
Summary: nice description
Home-page: http://github.com/SonihiK/calc001
Download-URL: https://github.com/SonihiK/calc001/
Author: seongji
Classifier: Programming Language :: Python :: 3
